ramses_cli/__init__.py
ramses_cli/client.py
ramses_cli/debug.py
ramses_cli/discovery.py
ramses_cli/py.typed
ramses_cli/utils/cat_slow.py
ramses_cli/utils/convert.py
ramses_rf/__init__.py
ramses_rf/binding_fsm.py
ramses_rf/const.py
ramses_rf/database.py
ramses_rf/dispatcher.py
ramses_rf/entity_base.py
ramses_rf/exceptions.py
ramses_rf/gateway.py
ramses_rf/helpers.py
ramses_rf/py.typed
ramses_rf/schemas.py
ramses_rf/storage.py
ramses_rf/version.py
ramses_rf/device/__init__.py
ramses_rf/device/base.py
ramses_rf/device/heat.py
ramses_rf/device/hvac.py
ramses_rf/system/__init__.py
ramses_rf/system/faultlog.py
ramses_rf/system/heat.py
ramses_rf/system/schedule.py
ramses_rf/system/zones.py
ramses_tx/__init__.py
ramses_tx/address.py
ramses_tx/command.py
ramses_tx/const.py
ramses_tx/exceptions.py
ramses_tx/fingerprints.py
ramses_tx/frame.py
ramses_tx/gateway.py
ramses_tx/helpers.py
ramses_tx/logger.py
ramses_tx/message.py
ramses_tx/opentherm.py
ramses_tx/packet.py
ramses_tx/parsers.py
ramses_tx/protocol.py
ramses_tx/protocol_fsm.py
ramses_tx/py.typed
ramses_tx/ramses.py
ramses_tx/schemas.py
ramses_tx/transport.py
ramses_tx/typed_dicts.py
ramses_tx/typing.py
ramses_tx/version.py
ramses_rf-0.53.5.dist-info/METADATA
ramses_rf-0.53.5.dist-info/WHEEL
ramses_rf-0.53.5.dist-info/entry_points.txt
ramses_rf-0.53.5.dist-info/licenses/LICENSE
ramses_rf-0.53.5.dist-info/RECORD
