Metadata-Version: 2.4
Name: ramses_rf
Version: 0.53.5
Summary: A stateful RAMSES-II protocol decoder & analyser.
Project-URL: Homepage, https://github.com/ramses-rf/ramses_rf
Project-URL: Bug Tracker, https://github.com/ramses-rf/ramses_rf/issues
Project-URL: Wiki, https://github.com/ramses-rf/ramses_rf/wiki
Author-email: David Bonnes <zxdavb@bonnes.me>, Egbert Broerse <dcc2@ebroerse.nl>
Maintainer-email: Egbert Broerse <dcc2@ebroerse.nl>
License-Expression: MIT
License-File: LICENSE
Keywords: airios,chronotherm,climarad,evohome,hometronics,honeywell,itho,nuaire,orcon,ramses,resideo,round thermostat,sundial,vasco
Classifier: Programming Language :: Python :: 3.13
Classifier: Topic :: Home Automation
Requires-Python: >=3.11
Requires-Dist: colorlog>=6.9.0
Requires-Dist: paho-mqtt>=2.1.0
Requires-Dist: pyserial-asyncio-fast>=0.16
Requires-Dist: voluptuous>=0.15.2
